umierrorcorrect2/__init__.py
umierrorcorrect2/align.py
umierrorcorrect2/batch.py
umierrorcorrect2/call_variants.py
umierrorcorrect2/cli.py
umierrorcorrect2/downsampling.py
umierrorcorrect2/get_consensus_statistics.py
umierrorcorrect2/pipeline.py
umierrorcorrect2/preprocess.py
umierrorcorrect2/qc.py
umierrorcorrect2/umi_error_correct.py
umierrorcorrect2/version.py
umierrorcorrect2/core/__init__.py
umierrorcorrect2/core/check_args.py
umierrorcorrect2/core/consensus.py
umierrorcorrect2/core/constants.py
umierrorcorrect2/core/filter.py
umierrorcorrect2/core/fit_background_model.py
umierrorcorrect2/core/get_cons_info.py
umierrorcorrect2/core/get_regions_from_bed.py
umierrorcorrect2/core/group.py
umierrorcorrect2/core/logging_config.py
umierrorcorrect2/core/read_fastq_records.py
umierrorcorrect2/core/umi_cluster.py
umierrorcorrect2/core/utils.py
umierrorcorrect2/models/__init__.py
umierrorcorrect2/models/models.py
umierrorcorrect2-0.32.0.dist-info/METADATA
umierrorcorrect2-0.32.0.dist-info/WHEEL
umierrorcorrect2-0.32.0.dist-info/entry_points.txt
umierrorcorrect2-0.32.0.dist-info/licenses/LICENSE.txt
umierrorcorrect2-0.32.0.dist-info/RECORD
