Metadata-Version: 2.4
Name: umierrorcorrect2
Version: 0.32.0
Summary: Pipeline for analyzing barcoded amplicon sequencing data with Unique Molecular Identifiers (UMI)
Project-URL: Homepage, https://github.com/sfilges/umierrorcorrect2
Project-URL: Documentation, https://github.com/sfilges/umierrorcorrect2/wiki
Project-URL: Repository, https://github.com/sfilges/umierrorcorrect2
Author-email: Stefan Filges <stefan.filges@pm.me>, Tobias Osterlund <tobias.osterlund@gu.se>
License-Expression: MIT
License-File: LICENSE.txt
Classifier: Programming Language :: Python :: 3
Classifier: Programming Language :: Python :: 3.10
Classifier: Programming Language :: Python :: 3.11
Classifier: Programming Language :: Python :: 3.12
Classifier: Programming Language :: Python :: 3.13
Classifier: Topic :: Scientific/Engineering :: Bio-Informatics
Requires-Python: >=3.10
Requires-Dist: cutadapt>=5.2
Requires-Dist: loguru>=0.7.0
Requires-Dist: matplotlib
Requires-Dist: multiqc>=1.33
Requires-Dist: numba>=0.57.0
Requires-Dist: pydantic>=2.12.0
Requires-Dist: pysam>=0.23.0
Requires-Dist: scipy
Requires-Dist: typer>=0.21.1
Provides-Extra: dev
Requires-Dist: mypy; extra == 'dev'
Requires-Dist: pre-commit; extra == 'dev'
Requires-Dist: pytest; extra == 'dev'
Requires-Dist: pytest-cov; extra == 'dev'
Requires-Dist: ruff; extra == 'dev'
